data_primer/__init__.py
data_primer/core.py
data_primer-0.0.3.dist-info/licenses/LICENSE
data_primer-0.0.3.dist-info/METADATA
data_primer-0.0.3.dist-info/WHEEL
data_primer-0.0.3.dist-info/top_level.txt
data_primer-0.0.3.dist-info/RECORD
